{"id":"mec-nica-de-juego---pok-mon-o-venezolano;criterio-1-4---finalizar-partida-tras-10-preguntas;chrome-147-0-7727-57;windows","name":"CRITERIO-1.4 — Finalizar partida tras 10 preguntas","title":"CRITERIO-1.4 — Finalizar partida tras 10 preguntas","manual":false,"testSteps":[{"number":1,"description":"Before","startTime":"2026-04-18T22:56:25.983Z","children":[],"reportData":[],"screenshots":[],"duration":880,"result":"SUCCESS"},{"number":2,"description":"Dado que el usuario accede a la pantalla del juego","startTime":"2026-04-18T22:56:26.863Z","children":[],"reportData":[],"screenshots":[],"duration":73,"result":"SUCCESS"},{"number":3,"description":"Cuando la página termina de cargar","startTime":"2026-04-18T22:56:26.937Z","children":[],"reportData":[],"screenshots":[],"duration":121,"result":"SUCCESS"},{"number":4,"description":"Y el usuario responde las 10 preguntas de la partida","startTime":"2026-04-18T22:56:27.058Z","children":[],"reportData":[],"screenshots":[],"duration":14793,"result":"SUCCESS"},{"number":5,"description":"Entonces el sistema navega automáticamente a la pantalla de resultados","startTime":"2026-04-18T22:56:41.852Z","children":[],"reportData":[],"screenshots":[],"duration":1549,"result":"SUCCESS"},{"number":6,"description":"Y muestra los aciertos, errores, porcentaje y el estado de la partida","startTime":"2026-04-18T22:56:43.401Z","children":[],"reportData":[],"screenshots":[],"duration":34,"result":"SUCCESS"},{"number":7,"description":"After","startTime":"2026-04-18T22:56:43.435Z","children":[],"reportData":[],"screenshots":[],"duration":1,"result":"SUCCESS"}],"userStory":{"id":"mec-nica-de-juego---pok-mon-o-venezolano","storyName":"Mecánica de Juego — Pokémon o Venezolano","displayName":"Mecánica de Juego — Pokémon o Venezolano","path":"gameplay/mecanica-juego","type":"feature","narrative":"Como usuario autenticado o invitado\nQuiero responder preguntas identificando términos como Pokémon o Venezolano\nPara entrenarme y acumular una puntuación en la partida","pathElements":[{"name":"gameplay","description":"Gameplay"},{"name":"mecanica-juego","description":"Mecanica-juego"}]},"startTime":"2026-04-18T22:56:25.981Z","context":"chrome,windows","driver":"chrome","tags":[{"name":"chrome 147.0.7727.57","type":"browser","browserName":"chrome","browserVersion":"147.0.7727.57","displayName":"chrome 147.0.7727.57"},{"name":"windows","type":"platform","platformName":"windows","platformVersion":"","displayName":"windows"},{"name":"Gameplay","type":"capability","displayName":"Gameplay"},{"name":"Gameplay/Mecánica de Juego — Pokémon o Venezolano","type":"feature","displayName":"Mecánica de Juego — Pokémon o Venezolano"},{"name":"happy-path","type":"tag","displayName":"happy-path"},{"name":"critico","type":"tag","displayName":"critico"}],"testSource":"JS","featureTag":{"name":"Gameplay/Mecánica de Juego — Pokémon o Venezolano","type":"feature","displayName":"Mecánica de Juego — Pokémon o Venezolano"},"result":"SUCCESS","duration":17470}